MANIFEST.in
README.txt
setup.py
postmaster/__init__.py
postmaster/conf.py
postmaster/http.py
postmaster/version.py
postmaster.egg-info/PKG-INFO
postmaster.egg-info/SOURCES.txt
postmaster.egg-info/dependency_links.txt
postmaster.egg-info/not-zip-safe
postmaster.egg-info/top_level.txt
test/__init__.py
test/test_pm.py
test/test_pycurl.py
test/test_urlfetch.py
test/test_urllib2.py