Metadata-Version: 1.0
Name: postmaster
Version: 0.9.3
Summary: Library for postmaster.io service
Home-page: http://postmaster.io
Author: Postmaster
Author-email: support@postmaster.com
License: UNKNOWN
Platform: UNKNOWN
